cyb600_huff1_lab1/__init__.py
cyb600_huff1_lab1/time_displayer.py
cyb600_huff1_lab1-0.1.4.dist-info/METADATA
cyb600_huff1_lab1-0.1.4.dist-info/WHEEL
cyb600_huff1_lab1-0.1.4.dist-info/top_level.txt
cyb600_huff1_lab1-0.1.4.dist-info/RECORD
