Metadata-Version: 2.1
Name: cyb600_huff1_lab1
Version: 0.1.4
Summary: This package creates a webserver that will spit out the current time
Home-page: https://github.com/dhuffCanisius/CYB600_Lab1
Author: Darnell Huff
Author-email: huff4@canisius.edu
Requires-Python: >=3.6
